[
    {
        "Date": "1995-03-06",
        "Open": 15.25,
        "High": 15.25,
        "Low": 14.75,
        "Close": 14.75,
        "Volume": 81400.0,
        "10sma": 14.425,
        "20sma": 14.175,
        "50sma": 13.41
    },
    {
        "Date": "1995-03-07",
        "Open": 14.75,
        "High": 15.25,
        "Low": 14.75,
        "Close": 15.0,
        "Volume": 104400.0,
        "10sma": 14.4875,
        "20sma": 14.2125,
        "50sma": 13.49
    },
    {
        "Date": "1995-03-08",
        "Open": 15.0,
        "High": 17.0,
        "Low": 15.0,
        "Close": 16.25,
        "Volume": 220000.0,
        "10sma": 14.6625,
        "20sma": 14.3375,
        "50sma": 13.595
    },
    {
        "Date": "1995-03-09",
        "Open": 17.0,
        "High": 17.75,
        "Low": 16.25,
        "Close": 17.0,
        "Volume": 252400.0,
        "10sma": 14.9625,
        "20sma": 14.5,
        "50sma": 13.715
    },
    {
        "Date": "1995-03-10",
        "Open": 17.0,
        "High": 17.0,
        "Low": 16.5,
        "Close": 16.75,
        "Volume": 101900.0,
        "10sma": 15.2125,
        "20sma": 14.65,
        "50sma": 13.82
    },
    {
        "Date": "1995-03-13",
        "Open": 17.0,
        "High": 17.25,
        "Low": 16.5,
        "Close": 17.25,
        "Volume": 35900.0,
        "10sma": 15.525,
        "20sma": 14.825,
        "50sma": 13.94
    },
    {
        "Date": "1995-03-14",
        "Open": 17.25,
        "High": 17.5,
        "Low": 17.0,
        "Close": 17.25,
        "Volume": 42900.0,
        "10sma": 15.825,
        "20sma": 14.9875,
        "50sma": 14.055
    },
    {
        "Date": "1995-03-15",
        "Open": 17.5,
        "High": 17.75,
        "Low": 17.0,
        "Close": 17.75,
        "Volume": 34500.0,
        "10sma": 16.175,
        "20sma": 15.175,
        "50sma": 14.185
    },
    {
        "Date": "1995-03-16",
        "Open": 17.75,
        "High": 17.75,
        "Low": 17.125,
        "Close": 17.25,
        "Volume": 121500.0,
        "10sma": 16.45,
        "20sma": 15.35,
        "50sma": 14.305
    },
    {
        "Date": "1995-03-17",
        "Open": 17.5,
        "High": 18.5,
        "Low": 17.5,
        "Close": 18.5,
        "Volume": 45400.0,
        "10sma": 16.775,
        "20sma": 15.5625,
        "50sma": 14.45
    },
    {
        "Date": "1995-03-20",
        "Open": 18.5,
        "High": 19.0,
        "Low": 18.0,
        "Close": 19.0,
        "Volume": 71900.0,
        "10sma": 17.2,
        "20sma": 15.8125,
        "50sma": 14.6
    },
    {
        "Date": "1995-03-21",
        "Open": 19.125,
        "High": 19.5,
        "Low": 18.5,
        "Close": 19.0,
        "Volume": 115900.0,
        "10sma": 17.6,
        "20sma": 16.04375,
        "50sma": 14.74
    },
    {
        "Date": "1995-03-22",
        "Open": 19.25,
        "High": 19.25,
        "Low": 18.75,
        "Close": 19.125,
        "Volume": 217900.0,
        "10sma": 17.8875,
        "20sma": 16.275,
        "50sma": 14.8825
    },
    {
        "Date": "1995-03-23",
        "Open": 19.5,
        "High": 19.75,
        "Low": 18.875,
        "Close": 18.875,
        "Volume": 62900.0,
        "10sma": 18.075,
        "20sma": 16.51875,
        "50sma": 14.985
    },
    {
        "Date": "1995-03-24",
        "Open": 18.875,
        "High": 19.5,
        "Low": 18.875,
        "Close": 19.5,
        "Volume": 38500.0,
        "10sma": 18.35,
        "20sma": 16.78125,
        "50sma": 15.09
    },
    {
        "Date": "1995-03-27",
        "Open": 19.5,
        "High": 19.5,
        "Low": 18.0,
        "Close": 18.5,
        "Volume": 46600.0,
        "10sma": 18.475,
        "20sma": 17.0,
        "50sma": 15.18
    },
    {
        "Date": "1995-03-28",
        "Open": 18.25,
        "High": 18.75,
        "Low": 17.0,
        "Close": 17.75,
        "Volume": 73000.0,
        "10sma": 18.525,
        "20sma": 17.175,
        "50sma": 15.265
    },
    {
        "Date": "1995-03-29",
        "Open": 17.75,
        "High": 17.75,
        "Low": 17.0,
        "Close": 17.125,
        "Volume": 97700.0,
        "10sma": 18.4625,
        "20sma": 17.31875,
        "50sma": 15.325
    },
    {
        "Date": "1995-03-30",
        "Open": 17.75,
        "High": 17.75,
        "Low": 15.75,
        "Close": 17.0,
        "Volume": 87800.0,
        "10sma": 18.4375,
        "20sma": 17.44375,
        "50sma": 15.38
    },
    {
        "Date": "1995-03-31",
        "Open": 17.5,
        "High": 17.75,
        "Low": 16.875,
        "Close": 17.75,
        "Volume": 54300.0,
        "10sma": 18.3625,
        "20sma": 17.56875,
        "50sma": 15.45
    },
    {
        "Date": "1995-04-03",
        "Open": 17.75,
        "High": 17.75,
        "Low": 17.25,
        "Close": 17.75,
        "Volume": 49500.0,
        "10sma": 18.2375,
        "20sma": 17.71875,
        "50sma": 15.53
    }
]