[
    {
        "Date": "2024-08-13",
        "Open": 6.6599998474,
        "High": 6.8200001717,
        "Low": 6.0,
        "Close": 6.5599999428,
        "Volume": 41300.0,
        "10sma": 7.3706000328100005,
        "20sma": 8.04879999161,
        "50sma": 9.49475996018
    },
    {
        "Date": "2024-08-14",
        "Open": 6.4800000191,
        "High": 6.5500001907,
        "Low": 6.3099999428,
        "Close": 6.5500001907,
        "Volume": 32600.0,
        "10sma": 7.219600009919999,
        "20sma": 7.911299991609999,
        "50sma": 9.397559967046
    },
    {
        "Date": "2024-08-15",
        "Open": 6.6999998093,
        "High": 7.9000000954,
        "Low": 6.3499999046,
        "Close": 7.1999998093,
        "Volume": 10300.0,
        "10sma": 7.1315999984800005,
        "20sma": 7.808799982075,
        "50sma": 9.318559970862
    },
    {
        "Date": "2024-08-16",
        "Open": 7.1199998856,
        "High": 7.8990001678,
        "Low": 7.1199998856,
        "Close": 7.5549998283,
        "Volume": 14200.0,
        "10sma": 7.12049999237,
        "20sma": 7.73654997349,
        "50sma": 9.249659967428
    },
    {
        "Date": "2024-08-19",
        "Open": 7.3400001526,
        "High": 7.8000001907,
        "Low": 7.1399998665,
        "Close": 7.8000001907,
        "Volume": 21700.0,
        "10sma": 7.166499996179999,
        "20sma": 7.704550004004998,
        "50sma": 9.197159967428
    },
    {
        "Date": "2024-08-20",
        "Open": 7.2600002289,
        "High": 7.6999998093,
        "Low": 7.0500001907,
        "Close": 7.3099999428,
        "Volume": 6600.0,
        "10sma": 7.1724999904599995,
        "20sma": 7.645050001145,
        "50sma": 9.121559963231999
    },
    {
        "Date": "2024-08-21",
        "Open": 7.5300002098,
        "High": 7.5300002098,
        "Low": 7.25,
        "Close": 7.3499999046,
        "Volume": 12300.0,
        "10sma": 7.18749999999,
        "20sma": 7.593549990654999,
        "50sma": 9.044559965138
    },
    {
        "Date": "2024-08-22",
        "Open": 7.1399998665,
        "High": 7.8899998665,
        "Low": 7.1399998665,
        "Close": 7.8899998665,
        "Volume": 15000.0,
        "10sma": 7.26649999618,
        "20sma": 7.56154999733,
        "50sma": 8.97475996018
    },
    {
        "Date": "2024-08-23",
        "Open": 7.8499999046,
        "High": 8.7399997711,
        "Low": 7.7550001144,
        "Close": 8.5699996948,
        "Volume": 11100.0,
        "10sma": 7.408499956120001,
        "20sma": 7.56154999733,
        "50sma": 8.917559947972
    },
    {
        "Date": "2024-08-26",
        "Open": 8.220000267,
        "High": 9.779999733,
        "Low": 8.0500001907,
        "Close": 9.1999998093,
        "Volume": 10600.0,
        "10sma": 7.59849991798,
        "20sma": 7.587549972535001,
        "50sma": 8.876159935002
    },
    {
        "Date": "2024-08-27",
        "Open": 9.0,
        "High": 9.3800001144,
        "Low": 8.9499998093,
        "Close": 9.3800001144,
        "Volume": 3700.0,
        "10sma": 7.88049993514,
        "20sma": 7.6255499839750005,
        "50sma": 8.839959945682
    },
    {
        "Date": "2024-08-28",
        "Open": 9.1999998093,
        "High": 9.4099998474,
        "Low": 9.1999998093,
        "Close": 9.3400001526,
        "Volume": 1100.0,
        "10sma": 8.15949993133,
        "20sma": 7.6895499706249995,
        "50sma": 8.806759948734
    },
    {
        "Date": "2024-08-29",
        "Open": 9.25,
        "High": 10.0,
        "Low": 9.029999733,
        "Close": 9.9399995804,
        "Volume": 6200.0,
        "10sma": 8.43349990844,
        "20sma": 7.78254995346,
        "50sma": 8.800559940342
    },
    {
        "Date": "2024-08-30",
        "Open": 9.8520002365,
        "High": 10.75,
        "Low": 9.3500003815,
        "Close": 10.6379995346,
        "Volume": 19400.0,
        "10sma": 8.74179987907,
        "20sma": 7.931149935720001,
        "50sma": 8.812519931795999
    },
    {
        "Date": "2024-09-03",
        "Open": 9.6099996567,
        "High": 10.6199998856,
        "Low": 9.6099996567,
        "Close": 10.6199998856,
        "Volume": 6200.0,
        "10sma": 9.02379984856,
        "20sma": 8.09514992237,
        "50sma": 8.8311199379
    },
    {
        "Date": "2024-09-04",
        "Open": 10.3500003815,
        "High": 10.4200000763,
        "Low": 9.8599996567,
        "Close": 10.2399997711,
        "Volume": 5400.0,
        "10sma": 9.31679983139,
        "20sma": 8.244649910925,
        "50sma": 8.831919937136
    },
    {
        "Date": "2024-09-05",
        "Open": 9.8299999237,
        "High": 10.0590000153,
        "Low": 9.3500003815,
        "Close": 9.7279996872,
        "Volume": 11200.0,
        "10sma": 9.55459980965,
        "20sma": 8.37104990482,
        "50sma": 8.827479934693999
    },
    {
        "Date": "2024-09-06",
        "Open": 9.8000001907,
        "High": 10.1350002289,
        "Low": 9.0,
        "Close": 9.2329998016,
        "Volume": 11700.0,
        "10sma": 9.68889980316,
        "20sma": 8.47769989967,
        "50sma": 8.800939922334
    },
    {
        "Date": "2024-09-09",
        "Open": 9.2229995728,
        "High": 9.2700004578,
        "Low": 8.4200000763,
        "Close": 8.5,
        "Volume": 30600.0,
        "10sma": 9.68189983368,
        "20sma": 8.5451998949,
        "50sma": 8.772139930726
    },
    {
        "Date": "2024-09-10",
        "Open": 8.0,
        "High": 8.3400001526,
        "Low": 8.0,
        "Close": 8.3299999237,
        "Volume": 1600.0,
        "10sma": 9.59489984512,
        "20sma": 8.59669988155,
        "50sma": 8.719739933014
    },
    {
        "Date": "2024-09-11",
        "Open": 8.3299999237,
        "High": 8.5,
        "Low": 8.1899995804,
        "Close": 8.3900003433,
        "Volume": 3200.0,
        "10sma": 9.495899868010001,
        "20sma": 8.688199901575,
        "50sma": 8.673539943694
    },
    {
        "Date": "2024-09-12",
        "Open": 8.3999996185,
        "High": 8.3999996185,
        "Low": 7.5399999619,
        "Close": 8.3760004044,
        "Volume": 10300.0,
        "10sma": 9.39949989319,
        "20sma": 8.77949991226,
        "50sma": 8.636659946442
    },
    {
        "Date": "2024-09-13",
        "Open": 8.2899999619,
        "High": 8.5850000381,
        "Low": 8.0229997635,
        "Close": 8.5799999237,
        "Volume": 8600.0,
        "10sma": 9.26349992752,
        "20sma": 8.84849991798,
        "50sma": 8.588459949494
    },
    {
        "Date": "2024-09-16",
        "Open": 8.3100004196,
        "High": 8.8000001907,
        "Low": 8.3100004196,
        "Close": 8.6899995804,
        "Volume": 7200.0,
        "10sma": 9.0686999321,
        "20sma": 8.905249905585,
        "50sma": 8.565259933472
    },
    {
        "Date": "2024-09-17",
        "Open": 8.7060003281,
        "High": 8.7760000229,
        "Low": 8.029999733,
        "Close": 8.2100000381,
        "Volume": 9800.0,
        "10sma": 8.827699947350002,
        "20sma": 8.925749897955,
        "50sma": 8.519659938812
    },
    {
        "Date": "2024-09-18",
        "Open": 8.1800003052,
        "High": 8.4849996567,
        "Low": 7.6399998665,
        "Close": 8.0100002289,
        "Volume": 5800.0,
        "10sma": 8.604699993130001,
        "20sma": 8.96074991226,
        "50sma": 8.482659950256
    },
    {
        "Date": "2024-09-19",
        "Open": 7.8099999428,
        "High": 8.75,
        "Low": 7.5,
        "Close": 8.1499996185,
        "Volume": 16200.0,
        "10sma": 8.446899986260002,
        "20sma": 9.000749897955,
        "50sma": 8.45165994644
    },
    {
        "Date": "2024-09-20",
        "Open": 8.0710000992,
        "High": 8.8699998856,
        "Low": 8.0710000992,
        "Close": 8.8699998856,
        "Volume": 11200.0,
        "10sma": 8.41059999466,
        "20sma": 9.049749898910001,
        "50sma": 8.433659934996
    },
    {
        "Date": "2024-09-23",
        "Open": 8.8999996185,
        "High": 9.25,
        "Low": 8.2399997711,
        "Close": 9.1999998093,
        "Volume": 7400.0,
        "10sma": 8.48059997559,
        "20sma": 9.081249904635,
        "50sma": 8.433059940338
    },
    {
        "Date": "2024-09-24",
        "Open": 9.5500001907,
        "High": 10.3400001526,
        "Low": 9.0,
        "Close": 10.0,
        "Volume": 21800.0,
        "10sma": 8.647599983220001,
        "20sma": 9.121249914169999,
        "50sma": 8.446519947052
    },
    {
        "Date": "2024-09-25",
        "Open": 9.5100002289,
        "High": 10.2700004578,
        "Low": 9.4099998474,
        "Close": 10.1999998093,
        "Volume": 11500.0,
        "10sma": 8.82859992982,
        "20sma": 9.162249898915,
        "50sma": 8.460519943238001
    },
    {
        "Date": "2024-09-26",
        "Open": 9.8100004196,
        "High": 10.3400001526,
        "Low": 9.4099998474,
        "Close": 10.3299999237,
        "Volume": 16300.0,
        "10sma": 9.02399988175,
        "20sma": 9.21174988747,
        "50sma": 8.481119937897999
    },
    {
        "Date": "2024-09-27",
        "Open": 10.2399997711,
        "High": 10.279999733,
        "Low": 9.9499998093,
        "Close": 10.25,
        "Volume": 11700.0,
        "10sma": 9.190999889379999,
        "20sma": 9.22724990845,
        "50sma": 8.501119937898
    },
    {
        "Date": "2024-09-30",
        "Open": 10.2899999619,
        "High": 12.0,
        "Low": 10.279999733,
        "Close": 11.9799995422,
        "Volume": 18500.0,
        "10sma": 9.51999988556,
        "20sma": 9.29434990883,
        "50sma": 8.560719928742
    },
    {
        "Date": "2024-10-01",
        "Open": 11.8100004196,
        "High": 12.25,
        "Low": 10.8599996567,
        "Close": 11.0100002289,
        "Volume": 32400.0,
        "10sma": 9.79999990464,
        "20sma": 9.313849925995001,
        "50sma": 8.612119941712
    },
    {
        "Date": "2024-10-02",
        "Open": 10.8549995422,
        "High": 11.0,
        "Low": 9.7790002823,
        "Close": 10.9799995422,
        "Volume": 5700.0,
        "10sma": 10.09699983597,
        "20sma": 9.35084991455,
        "50sma": 8.661719932556002
    },
    {
        "Date": "2024-10-03",
        "Open": 10.0,
        "High": 10.8999996185,
        "Low": 9.9899997711,
        "Close": 10.5,
        "Volume": 18000.0,
        "10sma": 10.331999874120001,
        "20sma": 9.38944993019,
        "50sma": 8.704119930268
    },
    {
        "Date": "2024-10-04",
        "Open": 10.1000003815,
        "High": 11.4099998474,
        "Low": 10.1000003815,
        "Close": 11.3000001907,
        "Volume": 12200.0,
        "10sma": 10.57499990463,
        "20sma": 9.492799949645,
        "50sma": 8.759519939422
    },
    {
        "Date": "2024-10-07",
        "Open": 10.9610004425,
        "High": 11.720000267,
        "Low": 10.3699998856,
        "Close": 11.3400001526,
        "Volume": 14900.0,
        "10sma": 10.78899993896,
        "20sma": 9.634799957275,
        "50sma": 8.814919948578
    },
    {
        "Date": "2024-10-08",
        "Open": 10.8999996185,
        "High": 11.8999996185,
        "Low": 10.8000001907,
        "Close": 11.1700000763,
        "Volume": 15600.0,
        "10sma": 10.90599994659,
        "20sma": 9.776799964904999,
        "50sma": 8.864719944
    },
    {
        "Date": "2024-10-09",
        "Open": 11.2100000381,
        "High": 11.8699998856,
        "Low": 10.8000001907,
        "Close": 11.8100004196,
        "Volume": 19400.0,
        "10sma": 11.06700000762,
        "20sma": 9.94779996872,
        "50sma": 8.92851995468
    },
    {
        "Date": "2024-10-10",
        "Open": 11.0,
        "High": 11.4469995499,
        "Low": 10.6700000763,
        "Close": 11.2399997711,
        "Volume": 5700.0,
        "10sma": 11.15799999236,
        "20sma": 10.090999937054999,
        "50sma": 8.99211994171
    },
    {
        "Date": "2024-10-11",
        "Open": 10.8500003815,
        "High": 11.0,
        "Low": 10.1780004501,
        "Close": 10.4499998093,
        "Volume": 5800.0,
        "10sma": 11.177999973290001,
        "20sma": 10.184499931335,
        "50sma": 9.039519939422
    },
    {
        "Date": "2024-10-14",
        "Open": 10.6999998093,
        "High": 11.0,
        "Low": 10.1000003815,
        "Close": 10.75,
        "Volume": 3800.0,
        "10sma": 11.05500001907,
        "20sma": 10.287499952314999,
        "50sma": 9.101199941634
    },
    {
        "Date": "2024-10-15",
        "Open": 10.3599996567,
        "High": 10.9600000381,
        "Low": 10.1000003815,
        "Close": 10.6999998093,
        "Volume": 16200.0,
        "10sma": 11.02399997711,
        "20sma": 10.411999940875,
        "50sma": 9.168399934768
    },
    {
        "Date": "2024-10-16",
        "Open": 10.3599996567,
        "High": 11.1000003815,
        "Low": 10.1999998093,
        "Close": 10.5,
        "Volume": 27600.0,
        "10sma": 10.97600002289,
        "20sma": 10.53649992943,
        "50sma": 9.233399934768
    },
    {
        "Date": "2024-10-17",
        "Open": 10.5,
        "High": 10.6820001602,
        "Low": 9.2700004578,
        "Close": 9.7600002289,
        "Volume": 20700.0,
        "10sma": 10.90200004578,
        "20sma": 10.61699995995,
        "50sma": 9.28459994316
    },
    {
        "Date": "2024-10-18",
        "Open": 10.0,
        "High": 11.2299995422,
        "Low": 9.75,
        "Close": 9.8800001144,
        "Volume": 13000.0,
        "10sma": 10.76000003815,
        "20sma": 10.667499971389999,
        "50sma": 9.340199947356
    },
    {
        "Date": "2024-10-21",
        "Open": 9.1339998245,
        "High": 9.9149999619,
        "Low": 9.1000003815,
        "Close": 9.3800001144,
        "Volume": 13700.0,
        "10sma": 10.564000034329998,
        "20sma": 10.676499986645,
        "50sma": 9.384799947736
    },
    {
        "Date": "2024-10-22",
        "Open": 9.1599998474,
        "High": 10.3800001144,
        "Low": 9.1000003815,
        "Close": 9.779999733,
        "Volume": 41900.0,
        "10sma": 10.425,
        "20sma": 10.665499973295,
        "50sma": 9.434399938582
    },
    {
        "Date": "2024-10-23",
        "Open": 10.7580003738,
        "High": 10.8999996185,
        "Low": 8.8649997711,
        "Close": 10.3999996185,
        "Volume": 88700.0,
        "10sma": 10.28399991989,
        "20sma": 10.675499963755,
        "50sma": 9.511199932096
    },
    {
        "Date": "2024-10-24",
        "Open": 10.0,
        "High": 10.8900003433,
        "Low": 9.7700004578,
        "Close": 10.1999998093,
        "Volume": 82100.0,
        "10sma": 10.17999992371,
        "20sma": 10.668999958034998,
        "50sma": 9.584199924468
    },
    {
        "Date": "2024-10-25",
        "Open": 10.1099996567,
        "High": 10.8900003433,
        "Low": 9.7600002289,
        "Close": 9.9899997711,
        "Volume": 15800.0,
        "10sma": 10.133999919889998,
        "20sma": 10.655999946589999,
        "50sma": 9.639999923704
    },
    {
        "Date": "2024-10-28",
        "Open": 10.3400001526,
        "High": 10.6949996948,
        "Low": 9.5399999619,
        "Close": 9.6999998093,
        "Volume": 19600.0,
        "10sma": 10.02899990082,
        "20sma": 10.541999959944999,
        "50sma": 9.682899923324
    },
    {
        "Date": "2024-10-29",
        "Open": 9.0100002289,
        "High": 9.6499996185,
        "Low": 9.0100002289,
        "Close": 9.5,
        "Volume": 13800.0,
        "10sma": 9.90899991989,
        "20sma": 10.4664999485,
        "50sma": 9.71689991951
    },
    {
        "Date": "2024-10-30",
        "Open": 9.5,
        "High": 11.6829996109,
        "Low": 9.5,
        "Close": 11.0880002975,
        "Volume": 67400.0,
        "10sma": 9.96779994964,
        "20sma": 10.471899986264999,
        "50sma": 9.792459926604
    }
]