[
    {
        "Date": "1998-01-15",
        "Open": 8.0625,
        "High": 8.0625,
        "Low": 7.625,
        "Close": 7.875,
        "Volume": 92800.0,
        "10sma": 8.2125,
        "20sma": 8.15,
        "50sma": 8.88125
    },
    {
        "Date": "1998-01-16",
        "Open": 8.0,
        "High": 8.0,
        "Low": 7.9375,
        "Close": 8.0,
        "Volume": 190800.0,
        "10sma": 8.2,
        "20sma": 8.134375,
        "50sma": 8.845
    },
    {
        "Date": "1998-01-20",
        "Open": 8.0,
        "High": 8.25,
        "Low": 8.0,
        "Close": 8.125,
        "Volume": 27700.0,
        "10sma": 8.15,
        "20sma": 8.134375,
        "50sma": 8.81125
    },
    {
        "Date": "1998-01-21",
        "Open": 8.25,
        "High": 8.5,
        "Low": 8.1875,
        "Close": 8.4375,
        "Volume": 30900.0,
        "10sma": 8.14375,
        "20sma": 8.146875,
        "50sma": 8.7825
    },
    {
        "Date": "1998-01-22",
        "Open": 8.3125,
        "High": 8.4375,
        "Low": 8.125,
        "Close": 8.4375,
        "Volume": 30800.0,
        "10sma": 8.14375,
        "20sma": 8.16875,
        "50sma": 8.76
    },
    {
        "Date": "1998-01-23",
        "Open": 8.5625,
        "High": 8.5625,
        "Low": 7.9375,
        "Close": 8.0,
        "Volume": 64400.0,
        "10sma": 8.13125,
        "20sma": 8.1625,
        "50sma": 8.7325
    },
    {
        "Date": "1998-01-26",
        "Open": 8.0,
        "High": 8.0,
        "Low": 7.8125,
        "Close": 7.875,
        "Volume": 30000.0,
        "10sma": 8.09375,
        "20sma": 8.153125,
        "50sma": 8.7025
    },
    {
        "Date": "1998-01-27",
        "Open": 8.0,
        "High": 8.0,
        "Low": 7.75,
        "Close": 7.9375,
        "Volume": 35800.0,
        "10sma": 8.075,
        "20sma": 8.14375,
        "50sma": 8.675
    },
    {
        "Date": "1998-01-28",
        "Open": 8.0625,
        "High": 8.125,
        "Low": 7.8125,
        "Close": 8.0,
        "Volume": 34100.0,
        "10sma": 8.0625,
        "20sma": 8.14375,
        "50sma": 8.64875
    },
    {
        "Date": "1998-01-29",
        "Open": 8.0,
        "High": 8.0,
        "Low": 7.875,
        "Close": 8.0,
        "Volume": 13700.0,
        "10sma": 8.06875,
        "20sma": 8.1375,
        "50sma": 8.62
    },
    {
        "Date": "1998-01-30",
        "Open": 7.9375,
        "High": 8.0625,
        "Low": 7.9375,
        "Close": 7.9375,
        "Volume": 32100.0,
        "10sma": 8.075,
        "20sma": 8.14375,
        "50sma": 8.59125
    },
    {
        "Date": "1998-02-02",
        "Open": 8.0,
        "High": 8.0,
        "Low": 7.875,
        "Close": 8.0,
        "Volume": 46100.0,
        "10sma": 8.075,
        "20sma": 8.1375,
        "50sma": 8.56
    },
    {
        "Date": "1998-02-03",
        "Open": 8.0,
        "High": 8.25,
        "Low": 7.8125,
        "Close": 8.0,
        "Volume": 140000.0,
        "10sma": 8.0625,
        "20sma": 8.10625,
        "50sma": 8.5275
    },
    {
        "Date": "1998-02-04",
        "Open": 8.125,
        "High": 8.1875,
        "Low": 7.9375,
        "Close": 8.1875,
        "Volume": 65600.0,
        "10sma": 8.0375,
        "20sma": 8.090625,
        "50sma": 8.49375
    },
    {
        "Date": "1998-02-05",
        "Open": 8.25,
        "High": 8.9375,
        "Low": 8.0625,
        "Close": 8.6875,
        "Volume": 297100.0,
        "10sma": 8.0625,
        "20sma": 8.103125,
        "50sma": 8.4725
    },
    {
        "Date": "1998-02-06",
        "Open": 9.0,
        "High": 9.1875,
        "Low": 8.875,
        "Close": 9.0,
        "Volume": 101600.0,
        "10sma": 8.1625,
        "20sma": 8.146875,
        "50sma": 8.4625
    },
    {
        "Date": "1998-02-09",
        "Open": 9.0,
        "High": 9.0,
        "Low": 8.75,
        "Close": 8.75,
        "Volume": 25500.0,
        "10sma": 8.25,
        "20sma": 8.171875,
        "50sma": 8.45
    },
    {
        "Date": "1998-02-10",
        "Open": 8.875,
        "High": 8.9375,
        "Low": 8.75,
        "Close": 8.8125,
        "Volume": 31200.0,
        "10sma": 8.3375,
        "20sma": 8.20625,
        "50sma": 8.43625
    },
    {
        "Date": "1998-02-11",
        "Open": 8.5625,
        "High": 8.875,
        "Low": 8.5625,
        "Close": 8.8125,
        "Volume": 24300.0,
        "10sma": 8.41875,
        "20sma": 8.240625,
        "50sma": 8.4225
    },
    {
        "Date": "1998-02-12",
        "Open": 8.8125,
        "High": 8.8125,
        "Low": 8.5,
        "Close": 8.625,
        "Volume": 15000.0,
        "10sma": 8.48125,
        "20sma": 8.275,
        "50sma": 8.405
    },
    {
        "Date": "1998-02-13",
        "Open": 8.75,
        "High": 8.75,
        "Low": 8.5,
        "Close": 8.6875,
        "Volume": 20200.0,
        "10sma": 8.55625,
        "20sma": 8.315625,
        "50sma": 8.39125
    },
    {
        "Date": "1998-02-17",
        "Open": 8.75,
        "High": 8.8125,
        "Low": 8.625,
        "Close": 8.75,
        "Volume": 20700.0,
        "10sma": 8.63125,
        "20sma": 8.353125,
        "50sma": 8.37875
    },
    {
        "Date": "1998-02-18",
        "Open": 8.875,
        "High": 8.9375,
        "Low": 8.5,
        "Close": 8.5625,
        "Volume": 53400.0,
        "10sma": 8.6875,
        "20sma": 8.375,
        "50sma": 8.36375
    },
    {
        "Date": "1998-02-19",
        "Open": 8.5,
        "High": 8.75,
        "Low": 8.4375,
        "Close": 8.625,
        "Volume": 163900.0,
        "10sma": 8.73125,
        "20sma": 8.384375,
        "50sma": 8.34875
    },
    {
        "Date": "1998-02-20",
        "Open": 8.5,
        "High": 8.75,
        "Low": 8.4375,
        "Close": 8.6875,
        "Volume": 59200.0,
        "10sma": 8.73125,
        "20sma": 8.396875,
        "50sma": 8.34125
    },
    {
        "Date": "1998-02-23",
        "Open": 8.5625,
        "High": 8.6875,
        "Low": 8.4375,
        "Close": 8.625,
        "Volume": 107700.0,
        "10sma": 8.69375,
        "20sma": 8.428125,
        "50sma": 8.33125
    },
    {
        "Date": "1998-02-24",
        "Open": 8.6875,
        "High": 8.6875,
        "Low": 8.5,
        "Close": 8.6875,
        "Volume": 46200.0,
        "10sma": 8.6875,
        "20sma": 8.46875,
        "50sma": 8.32375
    },
    {
        "Date": "1998-02-25",
        "Open": 8.5625,
        "High": 9.1875,
        "Low": 8.5625,
        "Close": 9.125,
        "Volume": 141100.0,
        "10sma": 8.71875,
        "20sma": 8.528125,
        "50sma": 8.33
    },
    {
        "Date": "1998-02-26",
        "Open": 9.1875,
        "High": 9.4375,
        "Low": 9.125,
        "Close": 9.375,
        "Volume": 140400.0,
        "10sma": 8.775,
        "20sma": 8.596875,
        "50sma": 8.3425
    },
    {
        "Date": "1998-02-27",
        "Open": 9.375,
        "High": 9.5,
        "Low": 9.375,
        "Close": 9.375,
        "Volume": 41000.0,
        "10sma": 8.85,
        "20sma": 8.665625,
        "50sma": 8.355
    },
    {
        "Date": "1998-03-02",
        "Open": 9.375,
        "High": 9.4375,
        "Low": 9.3125,
        "Close": 9.4375,
        "Volume": 55100.0,
        "10sma": 8.925,
        "20sma": 8.740625,
        "50sma": 8.37125
    },
    {
        "Date": "1998-03-03",
        "Open": 9.4375,
        "High": 9.5,
        "Low": 9.25,
        "Close": 9.3125,
        "Volume": 50500.0,
        "10sma": 8.98125,
        "20sma": 8.80625,
        "50sma": 8.39125
    },
    {
        "Date": "1998-03-04",
        "Open": 9.3125,
        "High": 9.375,
        "Low": 9.125,
        "Close": 9.375,
        "Volume": 38500.0,
        "10sma": 9.0625,
        "20sma": 8.875,
        "50sma": 8.41625
    },
    {
        "Date": "1998-03-05",
        "Open": 9.125,
        "High": 9.25,
        "Low": 9.0,
        "Close": 9.1875,
        "Volume": 35100.0,
        "10sma": 9.11875,
        "20sma": 8.925,
        "50sma": 8.43625
    },
    {
        "Date": "1998-03-06",
        "Open": 9.75,
        "High": 9.875,
        "Low": 9.5,
        "Close": 9.6875,
        "Volume": 210600.0,
        "10sma": 9.21875,
        "20sma": 8.975,
        "50sma": 8.47
    },
    {
        "Date": "1998-03-09",
        "Open": 9.75,
        "High": 10.0,
        "Low": 9.6875,
        "Close": 9.8125,
        "Volume": 122000.0,
        "10sma": 9.3375,
        "20sma": 9.015625,
        "50sma": 8.50375
    },
    {
        "Date": "1998-03-10",
        "Open": 9.875,
        "High": 9.9375,
        "Low": 9.75,
        "Close": 9.75,
        "Volume": 57000.0,
        "10sma": 9.44375,
        "20sma": 9.065625,
        "50sma": 8.5375
    },
    {
        "Date": "1998-03-11",
        "Open": 9.75,
        "High": 9.8125,
        "Low": 9.625,
        "Close": 9.6875,
        "Volume": 44600.0,
        "10sma": 9.5,
        "20sma": 9.109375,
        "50sma": 8.56875
    },
    {
        "Date": "1998-03-12",
        "Open": 9.6875,
        "High": 9.75,
        "Low": 9.625,
        "Close": 9.6875,
        "Volume": 40900.0,
        "10sma": 9.53125,
        "20sma": 9.153125,
        "50sma": 8.6025
    },
    {
        "Date": "1998-03-13",
        "Open": 9.6875,
        "High": 9.6875,
        "Low": 9.375,
        "Close": 9.375,
        "Volume": 98000.0,
        "10sma": 9.53125,
        "20sma": 9.190625,
        "50sma": 8.6275
    },
    {
        "Date": "1998-03-16",
        "Open": 9.5,
        "High": 9.5625,
        "Low": 9.3125,
        "Close": 9.3125,
        "Volume": 25900.0,
        "10sma": 9.51875,
        "20sma": 9.221875,
        "50sma": 8.6575
    },
    {
        "Date": "1998-03-17",
        "Open": 9.5,
        "High": 9.5625,
        "Low": 9.375,
        "Close": 9.375,
        "Volume": 70000.0,
        "10sma": 9.525,
        "20sma": 9.253125,
        "50sma": 8.6825
    },
    {
        "Date": "1998-03-18",
        "Open": 9.3125,
        "High": 9.375,
        "Low": 9.25,
        "Close": 9.3125,
        "Volume": 21200.0,
        "10sma": 9.51875,
        "20sma": 9.290625,
        "50sma": 8.69625
    },
    {
        "Date": "1998-03-19",
        "Open": 9.1875,
        "High": 9.25,
        "Low": 8.875,
        "Close": 9.0625,
        "Volume": 101500.0,
        "10sma": 9.50625,
        "20sma": 9.3125,
        "50sma": 8.7075
    },
    {
        "Date": "1998-03-20",
        "Open": 9.125,
        "High": 9.375,
        "Low": 9.0625,
        "Close": 9.125,
        "Volume": 25000.0,
        "10sma": 9.45,
        "20sma": 9.334375,
        "50sma": 8.72125
    },
    {
        "Date": "1998-03-23",
        "Open": 9.1875,
        "High": 9.25,
        "Low": 8.9375,
        "Close": 9.125,
        "Volume": 90600.0,
        "10sma": 9.38125,
        "20sma": 9.359375,
        "50sma": 8.74125
    },
    {
        "Date": "1998-03-24",
        "Open": 8.9375,
        "High": 9.25,
        "Low": 8.9375,
        "Close": 9.25,
        "Volume": 25200.0,
        "10sma": 9.33125,
        "20sma": 9.3875,
        "50sma": 8.76125
    },
    {
        "Date": "1998-03-25",
        "Open": 9.3125,
        "High": 9.375,
        "Low": 9.1875,
        "Close": 9.25,
        "Volume": 24300.0,
        "10sma": 9.2875,
        "20sma": 9.39375,
        "50sma": 8.78375
    },
    {
        "Date": "1998-03-26",
        "Open": 9.1875,
        "High": 9.4375,
        "Low": 9.1875,
        "Close": 9.3125,
        "Volume": 24500.0,
        "10sma": 9.25,
        "20sma": 9.390625,
        "50sma": 8.8075
    },
    {
        "Date": "1998-03-27",
        "Open": 9.375,
        "High": 9.375,
        "Low": 9.0,
        "Close": 9.0625,
        "Volume": 18900.0,
        "10sma": 9.21875,
        "20sma": 9.375,
        "50sma": 8.83
    },
    {
        "Date": "1998-03-30",
        "Open": 9.0625,
        "High": 9.1875,
        "Low": 8.9375,
        "Close": 9.0,
        "Volume": 27400.0,
        "10sma": 9.1875,
        "20sma": 9.353125,
        "50sma": 8.8525
    },
    {
        "Date": "1998-03-31",
        "Open": 9.5,
        "High": 10.75,
        "Low": 9.5,
        "Close": 10.4375,
        "Volume": 324700.0,
        "10sma": 9.29375,
        "20sma": 9.409375,
        "50sma": 8.90125
    },
    {
        "Date": "1998-04-01",
        "Open": 10.6875,
        "High": 11.5,
        "Low": 10.625,
        "Close": 11.1875,
        "Volume": 268000.0,
        "10sma": 9.48125,
        "20sma": 9.5,
        "50sma": 8.9625
    },
    {
        "Date": "1998-04-02",
        "Open": 11.625,
        "High": 11.625,
        "Low": 10.625,
        "Close": 11.0,
        "Volume": 149400.0,
        "10sma": 9.675,
        "20sma": 9.590625,
        "50sma": 9.01375
    },
    {
        "Date": "1998-04-03",
        "Open": 11.125,
        "High": 11.1875,
        "Low": 11.0,
        "Close": 11.125,
        "Volume": 42900.0,
        "10sma": 9.875,
        "20sma": 9.6625,
        "50sma": 9.0675
    },
    {
        "Date": "1998-04-06",
        "Open": 11.125,
        "High": 11.6875,
        "Low": 11.125,
        "Close": 11.6875,
        "Volume": 110000.0,
        "10sma": 10.13125,
        "20sma": 9.75625,
        "50sma": 9.14125
    },
    {
        "Date": "1998-04-07",
        "Open": 11.625,
        "High": 11.625,
        "Low": 10.875,
        "Close": 11.0,
        "Volume": 76700.0,
        "10sma": 10.30625,
        "20sma": 9.81875,
        "50sma": 9.20375
    },
    {
        "Date": "1998-04-08",
        "Open": 11.0,
        "High": 11.0,
        "Low": 10.5,
        "Close": 10.8125,
        "Volume": 44800.0,
        "10sma": 10.4625,
        "20sma": 9.875,
        "50sma": 9.26125
    },
    {
        "Date": "1998-04-09",
        "Open": 10.875,
        "High": 11.0,
        "Low": 10.625,
        "Close": 10.8125,
        "Volume": 26800.0,
        "10sma": 10.6125,
        "20sma": 9.93125,
        "50sma": 9.3175
    },
    {
        "Date": "1998-04-13",
        "Open": 10.875,
        "High": 10.875,
        "Low": 10.5,
        "Close": 10.75,
        "Volume": 13100.0,
        "10sma": 10.78125,
        "20sma": 10.0,
        "50sma": 9.3725
    },
    {
        "Date": "1998-04-14",
        "Open": 10.625,
        "High": 10.75,
        "Low": 10.25,
        "Close": 10.5625,
        "Volume": 33700.0,
        "10sma": 10.9375,
        "20sma": 10.0625,
        "50sma": 9.425
    },
    {
        "Date": "1998-04-15",
        "Open": 10.5,
        "High": 10.6875,
        "Low": 10.375,
        "Close": 10.5,
        "Volume": 109600.0,
        "10sma": 10.94375,
        "20sma": 10.11875,
        "50sma": 9.475
    },
    {
        "Date": "1998-04-16",
        "Open": 10.5625,
        "High": 10.625,
        "Low": 10.25,
        "Close": 10.3125,
        "Volume": 40000.0,
        "10sma": 10.85625,
        "20sma": 10.16875,
        "50sma": 9.52125
    },
    {
        "Date": "1998-04-17",
        "Open": 10.25,
        "High": 10.3125,
        "Low": 10.0,
        "Close": 10.25,
        "Volume": 41300.0,
        "10sma": 10.78125,
        "20sma": 10.228125,
        "50sma": 9.5625
    },
    {
        "Date": "1998-04-20",
        "Open": 10.25,
        "High": 12.4375,
        "Low": 10.25,
        "Close": 12.4375,
        "Volume": 372800.0,
        "10sma": 10.9125,
        "20sma": 10.39375,
        "50sma": 9.6375
    }
]