[
    {
        "Open": 56000.0,
        "High": 59000.00390625,
        "Low": 55000.00390625,
        "Close": 55000.00390625,
        "Volume": 0.0,
        "10sma": 58400.0,
        "20sma": 58750.0001953125,
        "50sma": 57611.2
    },
    {
        "Open": 55040.0,
        "High": 58000.0,
        "Low": 55000.00390625,
        "Close": 58000.0,
        "Volume": 3.0,
        "10sma": 58200.0,
        "20sma": 58650.0001953125,
        "50sma": 57811.2
    },
    {
        "Open": 55040.0,
        "High": 58000.0,
        "Low": 55000.00390625,
        "Close": 58000.0,
        "Volume": 0.0,
        "10sma": 58099.999609375,
        "20sma": 58500.000390625,
        "50sma": 58051.2
    },
    {
        "Open": 56000.0,
        "High": 56504.00390625,
        "Low": 56000.0,
        "Close": 56504.00390625,
        "Volume": 0.0,
        "10sma": 57750.4,
        "20sma": 58375.200390625,
        "50sma": 58241.28
    },
    {
        "Open": 58000.0,
        "High": 59000.00390625,
        "Low": 58000.0,
        "Close": 59000.00390625,
        "Volume": 0.0,
        "10sma": 57950.40078125,
        "20sma": 58375.200390625,
        "50sma": 58511.200078125
    },
    {
        "Open": 59000.00390625,
        "High": 59000.00390625,
        "Low": 59000.00390625,
        "Close": 59000.00390625,
        "Volume": 0.0,
        "10sma": 58150.4015625,
        "20sma": 58425.2005859375,
        "50sma": 58771.20015625
    },
    {
        "Open": 57504.0,
        "High": 57504.0,
        "Low": 57504.0,
        "Close": 57504.0,
        "Volume": 0.0,
        "10sma": 57900.8015625,
        "20sma": 58400.4005859375,
        "50sma": 58981.280078125
    },
    {
        "Open": 56999.99609375,
        "High": 56999.99609375,
        "Low": 56999.99609375,
        "Close": 56999.99609375,
        "Volume": 0.0,
        "10sma": 57600.801171875,
        "20sma": 58350.400390625,
        "50sma": 59201.28
    },
    {
        "Open": 57040.0,
        "High": 59000.00390625,
        "Low": 56999.99609375,
        "Close": 56999.99609375,
        "Volume": 0.0,
        "10sma": 57600.801171875,
        "20sma": 58300.4001953125,
        "50sma": 59381.279921875
    },
    {
        "Open": 59000.00390625,
        "High": 59000.00390625,
        "Low": 56999.99609375,
        "Close": 59000.00390625,
        "Volume": 0.0,
        "10sma": 57600.801171875,
        "20sma": 58250.400390625,
        "50sma": 59441.28
    },
    {
        "Open": 59040.0,
        "High": 60000.0,
        "Low": 59000.00390625,
        "Close": 60000.0,
        "Volume": 0.0,
        "10sma": 58100.80078125,
        "20sma": 58250.400390625,
        "50sma": 59461.279921875
    },
    {
        "Open": 58000.0,
        "High": 62000.0,
        "Low": 58000.0,
        "Close": 58000.0,
        "Volume": 3.0,
        "10sma": 58100.80078125,
        "20sma": 58150.400390625,
        "50sma": 59361.27984375
    },
    {
        "Open": 58000.0,
        "High": 62000.0,
        "Low": 58000.0,
        "Close": 62000.0,
        "Volume": 0.0,
        "10sma": 58500.80078125,
        "20sma": 58300.4001953125,
        "50sma": 59361.27984375
    },
    {
        "Open": 62000.0,
        "High": 62000.0,
        "Low": 58000.0,
        "Close": 62000.0,
        "Volume": 1.0,
        "10sma": 59050.400390625,
        "20sma": 58400.4001953125,
        "50sma": 59401.27984375
    },
    {
        "Open": 62000.0,
        "High": 62000.0,
        "Low": 62000.0,
        "Close": 62000.0,
        "Volume": 0.0,
        "10sma": 59350.4,
        "20sma": 58650.400390625,
        "50sma": 59441.27984375
    },
    {
        "Open": 58000.0,
        "High": 60999.99609375,
        "Low": 58000.0,
        "Close": 58000.0,
        "Volume": 2.0,
        "10sma": 59250.399609375,
        "20sma": 58700.4005859375,
        "50sma": 59401.27984375
    },
    {
        "Open": 58000.0,
        "High": 60999.99609375,
        "Low": 58000.0,
        "Close": 60999.99609375,
        "Volume": 0.0,
        "10sma": 59599.99921875,
        "20sma": 58750.400390625,
        "50sma": 59401.27984375
    },
    {
        "Open": 58000.0,
        "High": 60999.99609375,
        "Low": 58000.0,
        "Close": 60999.99609375,
        "Volume": 2.0,
        "10sma": 59999.99921875,
        "20sma": 58800.4001953125,
        "50sma": 59401.27984375
    },
    {
        "Open": 60999.99609375,
        "High": 60999.99609375,
        "Low": 59000.00390625,
        "Close": 60999.99609375,
        "Volume": 0.0,
        "10sma": 60399.99921875,
        "20sma": 59000.4001953125,
        "50sma": 59461.279765625
    },
    {
        "Open": 59000.00390625,
        "High": 59000.00390625,
        "Low": 59000.00390625,
        "Close": 59000.00390625,
        "Volume": 0.0,
        "10sma": 60399.99921875,
        "20sma": 59000.4001953125,
        "50sma": 59421.279921875
    },
    {
        "Open": 60999.99609375,
        "High": 60999.99609375,
        "Low": 60999.99609375,
        "Close": 60999.99609375,
        "Volume": 0.0,
        "10sma": 60499.998828125,
        "20sma": 59300.3998046875,
        "50sma": 59421.279921875
    },
    {
        "Open": 60999.99609375,
        "High": 60999.99609375,
        "Low": 60999.99609375,
        "Close": 60999.99609375,
        "Volume": 0.0,
        "10sma": 60799.9984375,
        "20sma": 59450.399609375,
        "50sma": 59441.27984375
    },
    {
        "Open": 60000.0,
        "High": 63000.00390625,
        "Low": 60000.0,
        "Close": 60999.99609375,
        "Volume": 5.0,
        "10sma": 60699.998046875,
        "20sma": 59600.3994140625,
        "50sma": 59440.479765625
    },
    {
        "Open": 60480.0,
        "High": 63000.00390625,
        "Low": 60000.0,
        "Close": 63000.00390625,
        "Volume": 1.0,
        "10sma": 60799.9984375,
        "20sma": 59925.1994140625,
        "50sma": 59500.47984375
    },
    {
        "Open": 63000.00390625,
        "High": 63000.00390625,
        "Low": 63000.00390625,
        "Close": 63000.00390625,
        "Volume": 0.0,
        "10sma": 60899.998828125,
        "20sma": 60125.1994140625,
        "50sma": 59540.48
    },
    {
        "Open": 63000.00390625,
        "High": 63000.00390625,
        "Low": 60000.0,
        "Close": 60000.0,
        "Volume": 3.0,
        "10sma": 61099.998828125,
        "20sma": 60175.19921875,
        "50sma": 59500.48
    }
]