[
    {
        "Date": "2023-06-05",
        "Open": 4.1199998856,
        "High": 4.1700000763,
        "Low": 3.7999999523,
        "Close": 3.9800000191,
        "Volume": 37400.0,
        "10sma": 4.40249996186,
        "20sma": 4.4379999876,
        "50sma": 4.592499980922
    },
    {
        "Date": "2023-06-06",
        "Open": 4.0700001717,
        "High": 4.3699998856,
        "Low": 4.0700001717,
        "Close": 4.3699998856,
        "Volume": 2400.0,
        "10sma": 4.37349996568,
        "20sma": 4.40024998188,
        "50sma": 4.59829998016
    },
    {
        "Date": "2023-06-07",
        "Open": 4.1799998283,
        "High": 4.2899999619,
        "Low": 3.7999999523,
        "Close": 4.1999998093,
        "Volume": 21900.0,
        "10sma": 4.343499946610001,
        "20sma": 4.375749969485001,
        "50sma": 4.59169997215
    },
    {
        "Date": "2023-06-08",
        "Open": 4.0500001907,
        "High": 4.1999998093,
        "Low": 4.0100002289,
        "Close": 4.1500000954,
        "Volume": 8900.0,
        "10sma": 4.3069999695,
        "20sma": 4.34324996472,
        "50sma": 4.583499975202
    },
    {
        "Date": "2023-06-09",
        "Open": 4.1100001335,
        "High": 4.1700000763,
        "Low": 4.0700001717,
        "Close": 4.0799999237,
        "Volume": 7700.0,
        "10sma": 4.26499996187,
        "20sma": 4.32474997044,
        "50sma": 4.573099975584
    },
    {
        "Date": "2023-06-12",
        "Open": 4.0900001526,
        "High": 4.2600002289,
        "Low": 4.0799999237,
        "Close": 4.2600002289,
        "Volume": 6600.0,
        "10sma": 4.24099998476,
        "20sma": 4.32474997044,
        "50sma": 4.559899978636
    },
    {
        "Date": "2023-06-13",
        "Open": 4.1100001335,
        "High": 4.4000000954,
        "Low": 3.9790000916,
        "Close": 4.1100001335,
        "Volume": 8900.0,
        "10sma": 4.21100001337,
        "20sma": 4.325249981885,
        "50sma": 4.549299983976
    },
    {
        "Date": "2023-06-14",
        "Open": 4.4400000572,
        "High": 4.5,
        "Low": 4.0900001526,
        "Close": 4.1999998093,
        "Volume": 18400.0,
        "10sma": 4.18600001337,
        "20sma": 4.321749973305,
        "50sma": 4.53629998207
    },
    {
        "Date": "2023-06-15",
        "Open": 4.3249998093,
        "High": 4.6599998474,
        "Low": 4.1599998474,
        "Close": 4.5,
        "Volume": 17500.0,
        "10sma": 4.19600000383,
        "20sma": 4.33174996377,
        "50sma": 4.534299983977999
    },
    {
        "Date": "2023-06-16",
        "Open": 4.8220000267,
        "High": 4.9000000954,
        "Low": 4.6649999619,
        "Close": 4.6999998093,
        "Volume": 25900.0,
        "10sma": 4.254999971409999,
        "20sma": 4.35474996568,
        "50sma": 4.53199997902
    },
    {
        "Date": "2023-06-20",
        "Open": 4.5500001907,
        "High": 4.5500001907,
        "Low": 3.9400000572,
        "Close": 4.1500000954,
        "Volume": 60000.0,
        "10sma": 4.27199997904,
        "20sma": 4.33724997045,
        "50sma": 4.512999982836
    },
    {
        "Date": "2023-06-21",
        "Open": 4.4000000954,
        "High": 4.5599999428,
        "Low": 4.3499999046,
        "Close": 4.3800001144,
        "Volume": 22700.0,
        "10sma": 4.27300000192,
        "20sma": 4.3232499838,
        "50sma": 4.504399986268
    },
    {
        "Date": "2023-06-22",
        "Open": 4.3000001907,
        "High": 4.4000000954,
        "Low": 4.1700000763,
        "Close": 4.25,
        "Volume": 8800.0,
        "10sma": 4.2780000209899995,
        "20sma": 4.3107499838,
        "50sma": 4.497399988176
    },
    {
        "Date": "2023-06-23",
        "Open": 4.3000001907,
        "High": 4.5679998398,
        "Low": 4.2199997902,
        "Close": 4.4800000191,
        "Volume": 16000.0,
        "10sma": 4.31100001336,
        "20sma": 4.30899999143,
        "50sma": 4.494999990466
    },
    {
        "Date": "2023-06-26",
        "Open": 4.5100002289,
        "High": 4.5799999237,
        "Low": 4.2199997902,
        "Close": 4.5100002289,
        "Volume": 9400.0,
        "10sma": 4.35400004388,
        "20sma": 4.309500002875,
        "50sma": 4.492599992755999
    },
    {
        "Date": "2023-06-27",
        "Open": 4.4000000954,
        "High": 4.5,
        "Low": 4.25,
        "Close": 4.5,
        "Volume": 1100.0,
        "10sma": 4.378000020989999,
        "20sma": 4.309500002875,
        "50sma": 4.486599988942
    },
    {
        "Date": "2023-06-28",
        "Open": 4.5,
        "High": 4.5500001907,
        "Low": 4.3600001335,
        "Close": 4.3600001335,
        "Volume": 4200.0,
        "10sma": 4.40300002099,
        "20sma": 4.30700001718,
        "50sma": 4.478599987034
    },
    {
        "Date": "2023-06-29",
        "Open": 4.2699999809,
        "High": 4.5,
        "Low": 4.2699999809,
        "Close": 4.5,
        "Volume": 15700.0,
        "10sma": 4.43300004006,
        "20sma": 4.309500026715,
        "50sma": 4.476199989322001
    },
    {
        "Date": "2023-06-30",
        "Open": 4.5700001717,
        "High": 4.5700001717,
        "Low": 4.4099998474,
        "Close": 4.4899997711,
        "Volume": 3600.0,
        "10sma": 4.43200001717,
        "20sma": 4.3140000105,
        "50sma": 4.470999984744
    },
    {
        "Date": "2023-07-03",
        "Open": 4.4200000763,
        "High": 4.4899997711,
        "Low": 4.4200000763,
        "Close": 4.4899997711,
        "Volume": 2400.0,
        "10sma": 4.41100001335,
        "20sma": 4.33299999238,
        "50sma": 4.468399982454
    },
    {
        "Date": "2023-07-05",
        "Open": 4.3899998665,
        "High": 4.3899998665,
        "Low": 4.2300000191,
        "Close": 4.2800002098,
        "Volume": 2800.0,
        "10sma": 4.42400002479,
        "20sma": 4.348000001915,
        "50sma": 4.468999986650001
    },
    {
        "Date": "2023-07-06",
        "Open": 4.2800002098,
        "High": 4.3899998665,
        "Low": 4.0599999428,
        "Close": 4.0599999428,
        "Volume": 6600.0,
        "10sma": 4.39200000763,
        "20sma": 4.332500004775,
        "50sma": 4.467399988176
    },
    {
        "Date": "2023-07-07",
        "Open": 4.1999998093,
        "High": 4.25,
        "Low": 4.1500000954,
        "Close": 4.2199997902,
        "Volume": 4100.0,
        "10sma": 4.388999986650001,
        "20sma": 4.33350000382,
        "50sma": 4.462999982836
    },
    {
        "Date": "2023-07-10",
        "Open": 4.2600002289,
        "High": 4.3200001717,
        "Low": 4.2399997711,
        "Close": 4.2399997711,
        "Volume": 2000.0,
        "10sma": 4.36499996185,
        "20sma": 4.337999987605,
        "50sma": 4.457999982836
    },
    {
        "Date": "2023-07-11",
        "Open": 4.1900000572,
        "High": 4.2899999619,
        "Low": 4.1199998856,
        "Close": 4.1300001144,
        "Volume": 6100.0,
        "10sma": 4.326999950399999,
        "20sma": 4.34049999714,
        "50sma": 4.440199985506
    },
    {
        "Date": "2023-07-12",
        "Open": 4.1399998665,
        "High": 4.2100000381,
        "Low": 4.1399998665,
        "Close": 4.1599998474,
        "Volume": 3300.0,
        "10sma": 4.29299993514,
        "20sma": 4.335499978065,
        "50sma": 4.423399982454
    },
    {
        "Date": "2023-07-13",
        "Open": 4.2100000381,
        "High": 4.4000000954,
        "Low": 4.1999998093,
        "Close": 4.1999998093,
        "Volume": 5100.0,
        "10sma": 4.27699990272,
        "20sma": 4.339999961855,
        "50sma": 4.409399976732001
    },
    {
        "Date": "2023-07-14",
        "Open": 4.3699998856,
        "High": 4.3699998856,
        "Low": 4.1900000572,
        "Close": 4.1900000572,
        "Volume": 1300.0,
        "10sma": 4.24599990844,
        "20sma": 4.339499974250001,
        "50sma": 4.394399976732
    },
    {
        "Date": "2023-07-17",
        "Open": 4.2550001144,
        "High": 4.3029999733,
        "Low": 4.1900000572,
        "Close": 4.1900000572,
        "Volume": 1100.0,
        "10sma": 4.215999937049999,
        "20sma": 4.323999977110001,
        "50sma": 4.380999975206
    },
    {
        "Date": "2023-07-18",
        "Open": 4.25,
        "High": 4.4000000954,
        "Low": 4.2100000381,
        "Close": 4.3899998665,
        "Volume": 4400.0,
        "10sma": 4.2059999465899995,
        "20sma": 4.30849997997,
        "50sma": 4.368999977114
    },
    {
        "Date": "2023-07-19",
        "Open": 4.3899998665,
        "High": 4.3899998665,
        "Low": 4.3000001907,
        "Close": 4.3000001907,
        "Volume": 1900.0,
        "10sma": 4.20799994468,
        "20sma": 4.315999984735,
        "50sma": 4.355999984742
    },
    {
        "Date": "2023-07-20",
        "Open": 4.3099999428,
        "High": 4.3099999428,
        "Low": 4.2800002098,
        "Close": 4.3000001907,
        "Volume": 1500.0,
        "10sma": 4.2319999694699995,
        "20sma": 4.31199998855,
        "50sma": 4.339499988556001
    },
    {
        "Date": "2023-07-21",
        "Open": 4.3000001907,
        "High": 4.3000001907,
        "Low": 3.9400000572,
        "Close": 4.1300001144,
        "Volume": 13800.0,
        "10sma": 4.223000001889999,
        "20sma": 4.30599999427,
        "50sma": 4.3282999897000005
    },
    {
        "Date": "2023-07-24",
        "Open": 4.2649998665,
        "High": 4.2649998665,
        "Low": 4.1500000954,
        "Close": 4.1500000954,
        "Volume": 1600.0,
        "10sma": 4.21400003432,
        "20sma": 4.289499998085,
        "50sma": 4.315299987794
    },
    {
        "Date": "2023-07-25",
        "Open": 4.1100001335,
        "High": 4.1999998093,
        "Low": 3.9100000858,
        "Close": 4.0,
        "Volume": 22100.0,
        "10sma": 4.20100002288,
        "20sma": 4.26399998664,
        "50sma": 4.306299991608
    },
    {
        "Date": "2023-07-26",
        "Open": 4.0500001907,
        "High": 4.1199998856,
        "Low": 4.0500001907,
        "Close": 4.1199998856,
        "Volume": 1200.0,
        "10sma": 4.1970000267000005,
        "20sma": 4.24499998092,
        "50sma": 4.303499984742
    },
    {
        "Date": "2023-07-27",
        "Open": 4.0199999809,
        "High": 4.1500000954,
        "Low": 4.0,
        "Close": 4.1500000954,
        "Volume": 2500.0,
        "10sma": 4.192000055309999,
        "20sma": 4.234499979015,
        "50sma": 4.304499988558
    },
    {
        "Date": "2023-07-28",
        "Open": 4.0999999046,
        "High": 4.0999999046,
        "Low": 4.0100002289,
        "Close": 4.0900001526,
        "Volume": 2100.0,
        "10sma": 4.18200006485,
        "20sma": 4.213999986645001,
        "50sma": 4.300899991992
    },
    {
        "Date": "2023-07-31",
        "Open": 4.1649999619,
        "High": 4.1700000763,
        "Low": 4.0100002289,
        "Close": 4.1500000954,
        "Volume": 1600.0,
        "10sma": 4.17800006867,
        "20sma": 4.197000002859999,
        "50sma": 4.297899990086
    },
    {
        "Date": "2023-08-01",
        "Open": 4.1500000954,
        "High": 4.2600002289,
        "Low": 4.1199998856,
        "Close": 4.1500000954,
        "Volume": 1800.0,
        "10sma": 4.15400009156,
        "20sma": 4.180000019075,
        "50sma": 4.296099996572
    },
    {
        "Date": "2023-08-02",
        "Open": 4.0500001907,
        "High": 4.1999998093,
        "Low": 4.0500001907,
        "Close": 4.1999998093,
        "Volume": 7200.0,
        "10sma": 4.144000053419999,
        "20sma": 4.175999999050001,
        "50sma": 4.290099992758
    },
    {
        "Date": "2023-08-03",
        "Open": 4.1929998398,
        "High": 4.1999998093,
        "Low": 4.0999999046,
        "Close": 4.0999999046,
        "Volume": 3400.0,
        "10sma": 4.12400002481,
        "20sma": 4.177999997140001,
        "50sma": 4.278899993902
    },
    {
        "Date": "2023-08-04",
        "Open": 4.2100000381,
        "High": 4.2100000381,
        "Low": 4.0,
        "Close": 4.1500000954,
        "Volume": 5500.0,
        "10sma": 4.1260000229100005,
        "20sma": 4.1745000124,
        "50sma": 4.27189999581
    },
    {
        "Date": "2023-08-07",
        "Open": 4.1799998283,
        "High": 4.1799998283,
        "Low": 4.0999999046,
        "Close": 4.0999999046,
        "Volume": 3800.0,
        "10sma": 4.12100000383,
        "20sma": 4.167500019075001,
        "50sma": 4.263599996572
    },
    {
        "Date": "2023-08-08",
        "Open": 4.1599998474,
        "High": 4.25,
        "Low": 4.0999999046,
        "Close": 4.0999999046,
        "Volume": 7600.0,
        "10sma": 4.13099999429,
        "20sma": 4.166000008585,
        "50sma": 4.255599994663999
    },
    {
        "Date": "2023-08-09",
        "Open": 4.3499999046,
        "High": 6.4499998093,
        "Low": 4.2030000687,
        "Close": 4.5,
        "Volume": 581600.0,
        "10sma": 4.16900000573,
        "20sma": 4.183000016215,
        "50sma": 4.255599994663999
    },
    {
        "Date": "2023-08-10",
        "Open": 4.3200001717,
        "High": 4.6500000954,
        "Low": 4.3200001717,
        "Close": 4.5,
        "Volume": 22900.0,
        "10sma": 4.20399999619,
        "20sma": 4.19800002575,
        "50sma": 4.257399997716
    },
    {
        "Date": "2023-08-11",
        "Open": 4.4299998283,
        "High": 4.5399999619,
        "Low": 4.2950000763,
        "Close": 4.5,
        "Volume": 25100.0,
        "10sma": 4.244999980929999,
        "20sma": 4.21350002289,
        "50sma": 4.25840000153
    },
    {
        "Date": "2023-08-14",
        "Open": 4.5999999046,
        "High": 4.8000001907,
        "Low": 4.3000001907,
        "Close": 4.4699997902,
        "Volume": 882200.0,
        "10sma": 4.27699995041,
        "20sma": 4.22750000954,
        "50sma": 4.259799995426
    },
    {
        "Date": "2023-08-15",
        "Open": 4.4400000572,
        "High": 4.7899999619,
        "Low": 4.4219999313,
        "Close": 4.5,
        "Volume": 67000.0,
        "10sma": 4.31199994087,
        "20sma": 4.233000016215,
        "50sma": 4.267599992756001
    },
    {
        "Date": "2023-08-16",
        "Open": 4.4600000381,
        "High": 4.5700001717,
        "Low": 4.2100000381,
        "Close": 4.4000000954,
        "Volume": 26400.0,
        "10sma": 4.33199996948,
        "20sma": 4.23800001145,
        "50sma": 4.275999994282
    },
    {
        "Date": "2023-08-17",
        "Open": 4.3499999046,
        "High": 4.4600000381,
        "Low": 4.2109999657,
        "Close": 4.4200000763,
        "Volume": 5400.0,
        "10sma": 4.36399998665,
        "20sma": 4.244000005729999,
        "50sma": 4.276999998096
    },
    {
        "Date": "2023-08-18",
        "Open": 4.4499998093,
        "High": 4.4899997711,
        "Low": 4.2899999619,
        "Close": 4.4899997711,
        "Volume": 13700.0,
        "10sma": 4.39799995422,
        "20sma": 4.261999988565,
        "50sma": 4.282799997332
    },
    {
        "Date": "2023-08-21",
        "Open": 4.5,
        "High": 5.1100001335,
        "Low": 4.5,
        "Close": 4.6999998093,
        "Volume": 50000.0,
        "10sma": 4.45799994469,
        "20sma": 4.28949997426,
        "50sma": 4.29379999161
    },
    {
        "Date": "2023-08-22",
        "Open": 4.6900000572,
        "High": 4.9200000763,
        "Low": 4.4000000954,
        "Close": 4.4899997711,
        "Volume": 32300.0,
        "10sma": 4.49699993134,
        "20sma": 4.313999962815,
        "50sma": 4.301999988558
    },
    {
        "Date": "2023-08-23",
        "Open": 4.5100002289,
        "High": 4.7800002098,
        "Low": 4.4299998283,
        "Close": 4.7800002098,
        "Volume": 16000.0,
        "10sma": 4.52499995232,
        "20sma": 4.346999979025,
        "50sma": 4.312399988176
    },
    {
        "Date": "2023-08-24",
        "Open": 4.7899999619,
        "High": 5.4899997711,
        "Low": 4.7899999619,
        "Close": 5.1599998474,
        "Volume": 498700.0,
        "10sma": 4.59099993706,
        "20sma": 4.397499966625,
        "50sma": 4.333399982454
    },
    {
        "Date": "2023-08-25",
        "Open": 5.2399997711,
        "High": 6.1999998093,
        "Low": 5.2399997711,
        "Close": 6.0,
        "Volume": 65200.0,
        "10sma": 4.740999937060001,
        "20sma": 4.492999958995,
        "50sma": 4.369399986268
    },
    {
        "Date": "2023-08-28",
        "Open": 6.4299998283,
        "High": 7.1599998474,
        "Low": 6.3000001907,
        "Close": 6.9699997902,
        "Volume": 114500.0,
        "10sma": 4.990999937060001,
        "20sma": 4.633999943735001,
        "50sma": 4.418799982072
    },
    {
        "Date": "2023-08-29",
        "Open": 6.9000000954,
        "High": 9.4709997177,
        "Low": 6.8210000992,
        "Close": 8.9099998474,
        "Volume": 677500.0,
        "10sma": 5.431999921800001,
        "20sma": 4.871999931335,
        "50sma": 4.502999982834
    }
]